lionclaw
