Metadata-Version: 1.1
Name: lionclaw
Version: 1.0.6
Summary: A shop for wagtail cms
Home-page: https://github.com/DarkArtek/lionclaw
Author: Luca Forzutti
Author-email: luca@ahd-creative.com
License: MIT
Keywords: lionclaw
Platform: UNKNOWN
Classifier: Development Status :: 3 - Alpha
Classifier: Framework :: Django
Classifier: Framework :: Django :: 2.0
Classifier: Intended Audience :: Developers
Classifier: License :: OSI Approved :: BSD License
Classifier: Natural Language :: English
Classifier: Programming Language :: Python :: 3
Classifier: Programming Language :: Python :: 3.3
Classifier: Programming Language :: Python :: 3.4
Classifier: Programming Language :: Python :: 3.5
Classifier: Programming Language :: Python :: 3.6
Classifier: Programming Language :: Python :: 3.7
Classifier: Programming Language :: Python :: 3.8
